requestx-0.2.8.dist-info/METADATA
requestx-0.2.8.dist-info/WHEEL
requestx/__init__.py
requestx/_requestx.abi3.so
requestx-0.2.8.dist-info/RECORD
