Metadata-Version: 2.4
Name: requestx
Version: 0.2.8
Classifier: Development Status :: 3 - Alpha
Classifier: Intended Audience :: Developers
Classifier: License :: OSI Approved :: MIT License
Classifier: Programming Language :: Python :: 3
Classifier: Programming Language :: Python :: 3.8
Classifier: Programming Language :: Python :: 3.9
Classifier: Programming Language :: Python :: 3.10
Classifier: Programming Language :: Python :: 3.11
Classifier: Programming Language :: Python :: 3.12
Classifier: Programming Language :: Rust
Classifier: Topic :: Internet :: WWW/HTTP
Classifier: Topic :: Software Development :: Libraries :: Python Modules
Requires-Dist: coverage>=7.6.1
Requires-Dist: maturin>=1.9.3
Requires-Dist: psutil>=7.0.0
Requires-Dist: tabulate>=0.9.0
Requires-Dist: httpx>=0.24 ; extra == 'dev'
Requires-Dist: aiohttp>=3.8 ; extra == 'dev'
Requires-Dist: requests>=2.28 ; extra == 'dev'
Requires-Dist: psutil>=7.0.0 ; extra == 'dev'
Requires-Dist: black>=23.0 ; extra == 'dev'
Requires-Dist: ruff>=0.1 ; extra == 'dev'
Requires-Dist: mypy>=1.0 ; extra == 'dev'
Requires-Dist: maturin>=1.9.1 ; extra == 'dev'
Provides-Extra: dev
Summary: High-performance HTTP client for Python with requests-compatible API
Keywords: http,requests,client,async,performance
Home-Page: https://github.com/neuesql/requestx
Author-email: RequestX Team <wu.qunfei@gmail.com>
License: MIT
Requires-Python: >=3.8
Project-URL: Homepage, https://github.com/neuesql/requestx
Project-URL: Repository, https://github.com/neuesql/requestx
Project-URL: Documentation, https://requestx.readthedocs.io
Project-URL: Bug Tracker, https://github.com/neuesql/requestx/issues
